pytest_playwright_snapshot/__init__.py
pytest_playwright_snapshot/plugin.py
pytest_playwright_snapshot-1.0.dist-info/METADATA
pytest_playwright_snapshot-1.0.dist-info/WHEEL
pytest_playwright_snapshot-1.0.dist-info/entry_points.txt
pytest_playwright_snapshot-1.0.dist-info/top_level.txt
pytest_playwright_snapshot-1.0.dist-info/RECORD
