Metadata-Version: 2.1
Name: pytest-playwright-snapshot
Version: 1.0
Summary: A pytest wrapper for snapshot testing with playwright
Home-page: https://github.com/kumaraditya303/pytest-playwright-snapshot
Author: Kumar Aditya
Author-email: 
License: UNKNOWN
Platform: UNKNOWN
Classifier: Programming Language :: Python :: 3
Classifier: Programming Language :: Python :: 3.7
Classifier: Programming Language :: Python :: 3.8
Classifier: Programming Language :: Python :: 3.9
Classifier: License :: OSI Approved :: Apache Software License
Classifier: Operating System :: OS Independent
Classifier: Framework :: Pytest
Requires-Python: >=3.7
Requires-Dist: pytest-playwright (>=0.1.2)
Requires-Dist: Pillow (>=8.2.0)
Requires-Dist: pixelmatch (==0.2.3)
